miniexplorer/__init__.py
miniexplorer/admin.py
miniexplorer/apps.py
miniexplorer/db.sqlite3
miniexplorer/models.py
miniexplorer/tests.py
miniexplorer/utils.py
miniexplorer/views.py
miniexplorer/__pycache__/__init__.cpython-312.pyc
miniexplorer/__pycache__/admin.cpython-312.pyc
miniexplorer/__pycache__/apps.cpython-312.pyc
miniexplorer/__pycache__/models.cpython-312.pyc
miniexplorer/__pycache__/utils.cpython-312.pyc
miniexplorer/fixtures/queries.json
miniexplorer/locale/pt_BR/LC_MESSAGES/django.mo
miniexplorer/locale/pt_BR/LC_MESSAGES/django.po
miniexplorer/locale/pt_BR/LC_MESSAGES/djangojs.mo
miniexplorer/locale/pt_BR/LC_MESSAGES/djangojs.po
miniexplorer/migrations/0001_initial.py
miniexplorer/migrations/0002_alter_query_options.py
miniexplorer/migrations/__init__.py
miniexplorer/migrations/__pycache__/0001_initial.cpython-312.pyc
miniexplorer/migrations/__pycache__/0002_alter_query_options.cpython-312.pyc
miniexplorer/migrations/__pycache__/__init__.cpython-312.pyc
miniexplorer/static/miniexplorer.css
miniexplorer/static/miniexplorer.js
miniexplorer/templates/schema_table.html
miniexplorer/templates/admin/miniexplorer/query/change_form.html
django_miniexplorer-0.6.1.dist-info/LICENSE
django_miniexplorer-0.6.1.dist-info/METADATA
django_miniexplorer-0.6.1.dist-info/WHEEL
django_miniexplorer-0.6.1.dist-info/top_level.txt
django_miniexplorer-0.6.1.dist-info/RECORD
