Metadata-Version: 2.1
Name: django-miniexplorer
Version: 0.6.1
Summary: Mini SQL Explorer for Django Admin
Home-page: https://github.com/dannluciano/django-miniexplorer
Author: Dann Luciano
Author-email: dannluciano@gmail.com
License: MIT
Keywords: django admin sql explorer database query
Requires-Python: >=3.6
License-File: LICENSE
